public final class jl
  implements Runnable
{
  public jl(boolean paramBoolean) {}
  
  /* Error */
  public final void run()
  {
    // Byte code:
    //   0: getstatic 36	java/lang/System:err	Ljava/io/PrintStream;
    //   3: ldc 9
    //   5: invokevirtual 54	java/io/PrintStream:println	(Ljava/lang/String;)V
    //   8: new 10	cM
    //   11: dup
    //   12: invokespecial 44	cM:<init>	()V
    //   15: invokestatic 80	xe:a	(LAd;)V
    //   18: aconst_null
    //   19: astore_1
    //   20: new 32	vg
    //   23: dup
    //   24: invokespecial 78	vg:<init>	()V
    //   27: astore_1
    //   28: goto +16 -> 44
    //   31: dup
    //   32: astore_2
    //   33: invokevirtual 66	java/sql/SQLException:printStackTrace	()V
    //   36: aload_2
    //   37: invokestatic 45	d:a	(Ljava/lang/Exception;)V
    //   40: iconst_m1
    //   41: invokestatic 64	java/lang/System:exit	(I)V
    //   44: new 28	org/schema/game/server/controller/GameServerController
    //   47: dup
    //   48: aload_1
    //   49: invokespecial 71	org/schema/game/server/controller/GameServerController:<init>	(Lvg;)V
    //   52: astore_2
    //   53: aconst_null
    //   54: astore_3
    //   55: iconst_0
    //   56: istore 4
    //   58: aload_0
    //   59: getfield 38	jl:jdField_a_of_type_Boolean	Z
    //   62: ifeq +17 -> 79
    //   65: new 31	pE
    //   68: dup
    //   69: aload_2
    //   70: invokespecial 76	pE:<init>	(Lorg/schema/schine/network/server/ServerController;)V
    //   73: dup
    //   74: astore_3
    //   75: iconst_1
    //   76: invokevirtual 77	pE:setVisible	(Z)V
    //   79: iconst_0
    //   80: putstatic 42	org/schema/game/common/Starter:c	Z
    //   83: aload_2
    //   84: invokevirtual 73	org/schema/game/server/controller/GameServerController:startServerAndListen	()V
    //   87: aload_2
    //   88: invokevirtual 72	org/schema/game/server/controller/GameServerController:isListenting	()Z
    //   91: ifne +18 -> 109
    //   94: ldc2_w 34
    //   97: invokestatic 65	java/lang/Thread:sleep	(J)V
    //   100: goto -13 -> 87
    //   103: invokevirtual 56	java/lang/InterruptedException:printStackTrace	()V
    //   106: goto -19 -> 87
    //   109: iconst_1
    //   110: putstatic 42	org/schema/game/common/Starter:c	Z
    //   113: new 13	java/io/File
    //   116: dup
    //   117: ldc 4
    //   119: invokespecial 49	java/io/File:<init>	(Ljava/lang/String;)V
    //   122: dup
    //   123: astore 5
    //   125: invokevirtual 52	java/io/File:exists	()Z
    //   128: ifeq +9 -> 137
    //   131: aload 5
    //   133: invokevirtual 51	java/io/File:delete	()Z
    //   136: pop
    //   137: aload 5
    //   139: invokevirtual 50	java/io/File:createNewFile	()Z
    //   142: pop
    //   143: new 12	java/io/DataOutputStream
    //   146: dup
    //   147: new 14	java/io/FileOutputStream
    //   150: dup
    //   151: aload 5
    //   153: invokespecial 53	java/io/FileOutputStream:<init>	(Ljava/io/File;)V
    //   156: invokespecial 46	java/io/DataOutputStream:<init>	(Ljava/io/OutputStream;)V
    //   159: astore_2
    //   160: aload_1
    //   161: invokevirtual 79	vg:getClients	()Ljava/util/HashMap;
    //   164: dup
    //   165: astore 5
    //   167: monitorenter
    //   168: aload_2
    //   169: aload_1
    //   170: invokevirtual 79	vg:getClients	()Ljava/util/HashMap;
    //   173: invokevirtual 67	java/util/HashMap:size	()I
    //   176: invokevirtual 48	java/io/DataOutputStream:writeInt	(I)V
    //   179: aload 5
    //   181: monitorexit
    //   182: goto +9 -> 191
    //   185: astore_1
    //   186: aload 5
    //   188: monitorexit
    //   189: aload_1
    //   190: athrow
    //   191: aload_2
    //   192: invokevirtual 47	java/io/DataOutputStream:close	()V
    //   195: iconst_1
    //   196: putstatic 41	org/schema/game/common/Starter:b	Z
    //   199: getstatic 39	org/schema/game/common/Starter:jdField_a_of_type_JavaLangObject	Ljava/lang/Object;
    //   202: dup
    //   203: astore 5
    //   205: monitorenter
    //   206: getstatic 39	org/schema/game/common/Starter:jdField_a_of_type_JavaLangObject	Ljava/lang/Object;
    //   209: invokevirtual 58	java/lang/Object:notify	()V
    //   212: aload 5
    //   214: monitorexit
    //   215: return
    //   216: astore_1
    //   217: aload 5
    //   219: monitorexit
    //   220: aload_1
    //   221: athrow
    //   222: astore 5
    //   224: aload_3
    //   225: ifnull +8 -> 233
    //   228: aload_3
    //   229: iconst_0
    //   230: invokevirtual 77	pE:setVisible	(Z)V
    //   233: aload 5
    //   235: instanceof 29
    //   238: ifeq +133 -> 371
    //   241: aload 5
    //   243: checkcast 29	org/schema/schine/network/exception/ServerPortNotAvailableException
    //   246: dup
    //   247: astore_2
    //   248: invokevirtual 74	org/schema/schine/network/exception/ServerPortNotAvailableException:isInstanceRunning	()Z
    //   251: ifeq +76 -> 327
    //   254: getstatic 37	java/lang/System:out	Ljava/io/PrintStream;
    //   257: new 20	java/lang/StringBuilder
    //   260: dup
    //   261: ldc 7
    //   263: invokespecial 59	java/lang/StringBuilder:<init>	(Ljava/lang/String;)V
    //   266: getstatic 43	org/schema/schine/network/server/ServerController:port	I
    //   269: invokevirtual 60	java/lang/StringBuilder:append	(I)Ljava/lang/StringBuilder;
    //   272: ldc 2
    //   274: invokevirtual 61	java/lang/StringBuilder:append	(Ljava/lang/String;)Ljava/lang/StringBuilder;
    //   277: getstatic 40	org/schema/game/common/Starter:jdField_a_of_type_Boolean	Z
    //   280: invokevirtual 62	java/lang/StringBuilder:append	(Z)Ljava/lang/StringBuilder;
    //   283: invokevirtual 63	java/lang/StringBuilder:toString	()Ljava/lang/String;
    //   286: invokevirtual 54	java/io/PrintStream:println	(Ljava/lang/String;)V
    //   289: getstatic 40	org/schema/game/common/Starter:jdField_a_of_type_Boolean	Z
    //   292: ifeq +76 -> 368
    //   295: getstatic 36	java/lang/System:err	Ljava/io/PrintStream;
    //   298: ldc 6
    //   300: invokevirtual 54	java/io/PrintStream:println	(Ljava/lang/String;)V
    //   303: new 20	java/lang/StringBuilder
    //   306: dup
    //   307: ldc 5
    //   309: invokespecial 59	java/lang/StringBuilder:<init>	(Ljava/lang/String;)V
    //   312: getstatic 43	org/schema/schine/network/server/ServerController:port	I
    //   315: invokevirtual 60	java/lang/StringBuilder:append	(I)Ljava/lang/StringBuilder;
    //   318: invokevirtual 63	java/lang/StringBuilder:toString	()Ljava/lang/String;
    //   321: invokestatic 70	org/schema/game/common/Starter:c	(Ljava/lang/String;)V
    //   324: goto +52 -> 376
    //   327: aload_2
    //   328: invokevirtual 75	org/schema/schine/network/exception/ServerPortNotAvailableException:printStackTrace	()V
    //   331: getstatic 37	java/lang/System:out	Ljava/io/PrintStream;
    //   334: new 20	java/lang/StringBuilder
    //   337: dup
    //   338: ldc 8
    //   340: invokespecial 59	java/lang/StringBuilder:<init>	(Ljava/lang/String;)V
    //   343: getstatic 43	org/schema/schine/network/server/ServerController:port	I
    //   346: invokevirtual 60	java/lang/StringBuilder:append	(I)Ljava/lang/StringBuilder;
    //   349: ldc 3
    //   351: invokevirtual 61	java/lang/StringBuilder:append	(Ljava/lang/String;)Ljava/lang/StringBuilder;
    //   354: invokevirtual 63	java/lang/StringBuilder:toString	()Ljava/lang/String;
    //   357: invokevirtual 54	java/io/PrintStream:println	(Ljava/lang/String;)V
    //   360: ldc 1
    //   362: invokestatic 69	org/schema/game/common/Starter:a	(Ljava/lang/String;)V
    //   365: iconst_1
    //   366: istore 4
    //   368: goto +8 -> 376
    //   371: aload 5
    //   373: invokevirtual 55	java/lang/Exception:printStackTrace	()V
    //   376: iload 4
    //   378: ifne +30 -> 408
    //   381: iconst_1
    //   382: putstatic 41	org/schema/game/common/Starter:b	Z
    //   385: getstatic 39	org/schema/game/common/Starter:jdField_a_of_type_JavaLangObject	Ljava/lang/Object;
    //   388: dup
    //   389: astore 5
    //   391: monitorenter
    //   392: getstatic 39	org/schema/game/common/Starter:jdField_a_of_type_JavaLangObject	Ljava/lang/Object;
    //   395: invokevirtual 58	java/lang/Object:notify	()V
    //   398: aload 5
    //   400: monitorexit
    //   401: return
    //   402: astore_1
    //   403: aload 5
    //   405: monitorexit
    //   406: aload_1
    //   407: athrow
    //   408: goto -408 -> 0
    //   411: astore_1
    //   412: iload 4
    //   414: ifne +29 -> 443
    //   417: iconst_1
    //   418: putstatic 41	org/schema/game/common/Starter:b	Z
    //   421: getstatic 39	org/schema/game/common/Starter:jdField_a_of_type_JavaLangObject	Ljava/lang/Object;
    //   424: dup
    //   425: astore_2
    //   426: monitorenter
    //   427: getstatic 39	org/schema/game/common/Starter:jdField_a_of_type_JavaLangObject	Ljava/lang/Object;
    //   430: invokevirtual 58	java/lang/Object:notify	()V
    //   433: aload_2
    //   434: monitorexit
    //   435: goto +12 -> 447
    //   438: astore_1
    //   439: aload_2
    //   440: monitorexit
    //   441: aload_1
    //   442: athrow
    //   443: aload_0
    //   444: invokevirtual 68	jl:run	()V
    //   447: aload_1
    //   448: athrow
    // Line number table:
    //   Java source line #815	-> byte code offset #0
    //   Java source line #819	-> byte code offset #8
    //   Java source line #820	-> byte code offset #18
    //   Java source line #822	-> byte code offset #20
    //   Java source line #827	-> byte code offset #28
    //   Java source line #823	-> byte code offset #31
    //   Java source line #824	-> byte code offset #32
    //   Java source line #825	-> byte code offset #36
    //   Java source line #826	-> byte code offset #40
    //   Java source line #828	-> byte code offset #44
    //   Java source line #829	-> byte code offset #53
    //   Java source line #830	-> byte code offset #55
    //   Java source line #831	-> byte code offset #58
    //   Java source line #832	-> byte code offset #65
    //   Java source line #833	-> byte code offset #74
    //   Java source line #835	-> byte code offset #79
    //   Java source line #837	-> byte code offset #83
    //   Java source line #839	-> byte code offset #87
    //   Java source line #841	-> byte code offset #94
    //   Java source line #844	-> byte code offset #100
    //   Java source line #842	-> byte code offset #103
    //   Java source line #844	-> byte code offset #106
    //   Java source line #846	-> byte code offset #109
    //   Java source line #848	-> byte code offset #113
    //   Java source line #849	-> byte code offset #123
    //   Java source line #850	-> byte code offset #131
    //   Java source line #852	-> byte code offset #137
    //   Java source line #853	-> byte code offset #143
    //   Java source line #854	-> byte code offset #160
    //   Java source line #855	-> byte code offset #168
    //   Java source line #856	-> byte code offset #179
    //   Java source line #857	-> byte code offset #191
    //   Java source line #882	-> byte code offset #195
    //   Java source line #884	-> byte code offset #199
    //   Java source line #885	-> byte code offset #206
    //   Java source line #886	-> byte code offset #212
    //   Java source line #888	-> byte code offset #222
    //   Java source line #859	-> byte code offset #224
    //   Java source line #860	-> byte code offset #228
    //   Java source line #862	-> byte code offset #233
    //   Java source line #863	-> byte code offset #241
    //   Java source line #864	-> byte code offset #247
    //   Java source line #865	-> byte code offset #254
    //   Java source line #866	-> byte code offset #289
    //   Java source line #867	-> byte code offset #295
    //   Java source line #868	-> byte code offset #303
    //   Java source line #871	-> byte code offset #327
    //   Java source line #872	-> byte code offset #331
    //   Java source line #873	-> byte code offset #360
    //   Java source line #874	-> byte code offset #365
    //   Java source line #876	-> byte code offset #368
    //   Java source line #877	-> byte code offset #371
    //   Java source line #882	-> byte code offset #376
    //   Java source line #883	-> byte code offset #381
    //   Java source line #884	-> byte code offset #385
    //   Java source line #885	-> byte code offset #392
    //   Java source line #886	-> byte code offset #398
    //   Java source line #888	-> byte code offset #408
    //   Java source line #890	-> byte code offset #411
    //   Java source line #883	-> byte code offset #417
    //   Java source line #884	-> byte code offset #421
    //   Java source line #885	-> byte code offset #427
    //   Java source line #886	-> byte code offset #433
    //   Java source line #888	-> byte code offset #443
    // Local variable table:
    //   start	length	slot	name	signature
    //   0	449	0	this	jl
    //   19	151	1	localvg	vg
    //   185	5	1	localObject1	Object
    //   216	5	1	localObject2	Object
    //   402	5	1	localObject3	Object
    //   411	1	1	localObject4	Object
    //   438	10	1	localObject5	Object
    //   32	296	2	localObject6	Object
    //   54	175	3	localpE	pE
    //   56	357	4	i	int
    //   123	29	5	localFile	java.io.File
    //   31	1	13	localSQLException	java.sql.SQLException
    //   103	1	14	localInterruptedException	java.lang.InterruptedException
    // Exception table:
    //   from	to	target	type
    //   20	28	31	java/sql/SQLException
    //   94	100	103	java/lang/InterruptedException
    //   168	182	185	finally
    //   206	215	216	finally
    //   83	195	222	java/lang/Exception
    //   392	401	402	finally
    //   83	195	411	finally
    //   222	376	411	finally
    //   427	435	438	finally
  }
}


/* Location:           C:\Users\Raul\Desktop\StarMade\StarMade.jar
 * Qualified Name:     jl
 * JD-Core Version:    0.7.0-SNAPSHOT-20130630
 */