/*      */ import java.util.ArrayList;
/*      */ import org.schema.game.common.data.world.Universe;
/*      */ 
/*      */ final class mz
/*      */   implements Runnable
/*      */ {
/*      */   mz(mx parammx, ArrayList paramArrayList, int paramInt, Universe paramUniverse)
/*      */   {
/*      */   }
/*      */ 
/*      */   // ERROR //
/*      */   public final void run()
/*      */   {
/*      */     // Byte code:
/*      */     //   0: aload_0
/*      */     //   1: getfield 30	mz:jdField_a_of_type_Mx	Lmx;
/*      */     //   4: invokestatic 50	mx:a	(Lmx;)Ljava/lang/Object;
/*      */     //   7: dup
/*      */     //   8: astore_1
/*      */     //   9: monitorenter
/*      */     //   10: getstatic 32	mz:jdField_a_of_type_Boolean	Z
/*      */     //   13: ifne +21 -> 34
/*      */     //   16: aload_0
/*      */     //   17: getfield 30	mz:jdField_a_of_type_Mx	Lmx;
/*      */     //   20: getfield 27	mx:jdField_a_of_type_Vg	Lvg;
/*      */     //   23: ifnonnull +11 -> 34
/*      */     //   26: new 8	java/lang/AssertionError
/*      */     //   29: dup
/*      */     //   30: invokespecial 35	java/lang/AssertionError:<init>	()V
/*      */     //   33: athrow
/*      */     //   34: getstatic 32	mz:jdField_a_of_type_Boolean	Z
/*      */     //   37: ifne +24 -> 61
/*      */     //   40: aload_0
/*      */     //   41: getfield 30	mz:jdField_a_of_type_Mx	Lmx;
/*      */     //   44: getfield 27	mx:jdField_a_of_type_Vg	Lvg;
/*      */     //   47: invokevirtual 54	vg:a	()Lorg/schema/game/common/controller/database/DatabaseIndex;
/*      */     //   50: ifnonnull +11 -> 61
/*      */     //   53: new 8	java/lang/AssertionError
/*      */     //   56: dup
/*      */     //   57: invokespecial 35	java/lang/AssertionError:<init>	()V
/*      */     //   60: athrow
/*      */     //   61: getstatic 32	mz:jdField_a_of_type_Boolean	Z
/*      */     //   64: ifne +18 -> 82
/*      */     //   67: aload_0
/*      */     //   68: getfield 30	mz:jdField_a_of_type_Mx	Lmx;
/*      */     //   71: ifnonnull +11 -> 82
/*      */     //   74: new 8	java/lang/AssertionError
/*      */     //   77: dup
/*      */     //   78: invokespecial 35	java/lang/AssertionError:<init>	()V
/*      */     //   81: athrow
/*      */     //   82: aload_0
/*      */     //   83: getfield 30	mz:jdField_a_of_type_Mx	Lmx;
/*      */     //   86: getfield 27	mx:jdField_a_of_type_Vg	Lvg;
/*      */     //   89: invokevirtual 54	vg:a	()Lorg/schema/game/common/controller/database/DatabaseIndex;
/*      */     //   92: aload_0
/*      */     //   93: getfield 30	mz:jdField_a_of_type_Mx	Lmx;
/*      */     //   96: invokevirtual 53	org/schema/game/common/controller/database/DatabaseIndex:a	(Lmx;)V
/*      */     //   99: invokestatic 45	java/lang/System:currentTimeMillis	()J
/*      */     //   102: lstore_2
/*      */     //   103: iconst_0
/*      */     //   104: istore 4
/*      */     //   106: iload 4
/*      */     //   108: aload_0
/*      */     //   109: getfield 29	mz:jdField_a_of_type_JavaUtilArrayList	Ljava/util/ArrayList;
/*      */     //   112: invokevirtual 48	java/util/ArrayList:size	()I
/*      */     //   115: if_icmpge +48 -> 163
/*      */     //   118: aload_0
/*      */     //   119: getfield 30	mz:jdField_a_of_type_Mx	Lmx;
/*      */     //   122: aload_0
/*      */     //   123: getfield 29	mz:jdField_a_of_type_JavaUtilArrayList	Ljava/util/ArrayList;
/*      */     //   126: iload 4
/*      */     //   128: invokevirtual 47	java/util/ArrayList:get	(I)Ljava/lang/Object;
/*      */     //   131: checkcast 21	org/schema/schine/network/objects/Sendable
/*      */     //   134: aload_0
/*      */     //   135: getfield 28	mz:jdField_a_of_type_Int	I
/*      */     //   138: aload_0
/*      */     //   139: getfield 31	mz:jdField_a_of_type_OrgSchemaGameCommonDataWorldUniverse	Lorg/schema/game/common/data/world/Universe;
/*      */     //   142: invokestatic 52	mx:a	(Lmx;Lorg/schema/schine/network/objects/Sendable;ILorg/schema/game/common/data/world/Universe;)V
/*      */     //   145: goto +12 -> 157
/*      */     //   148: invokevirtual 33	java/io/IOException:printStackTrace	()V
/*      */     //   151: goto +6 -> 157
/*      */     //   154: invokevirtual 37	java/lang/Exception:printStackTrace	()V
/*      */     //   157: iinc 4 1
/*      */     //   160: goto -54 -> 106
/*      */     //   163: invokestatic 45	java/lang/System:currentTimeMillis	()J
/*      */     //   166: lload_2
/*      */     //   167: lsub
/*      */     //   168: ldc2_w 23
/*      */     //   171: lcmp
/*      */     //   172: ifle +79 -> 251
/*      */     //   175: getstatic 25	java/lang/System:err	Ljava/io/PrintStream;
/*      */     //   178: new 13	java/lang/StringBuilder
/*      */     //   181: dup
/*      */     //   182: ldc 5
/*      */     //   184: invokespecial 39	java/lang/StringBuilder:<init>	(Ljava/lang/String;)V
/*      */     //   187: aload_0
/*      */     //   188: getfield 30	mz:jdField_a_of_type_Mx	Lmx;
/*      */     //   191: invokevirtual 49	mx:a	()I
/*      */     //   194: invokevirtual 40	java/lang/StringBuilder:append	(I)Ljava/lang/StringBuilder;
/*      */     //   197: ldc 1
/*      */     //   199: invokevirtual 43	java/lang/StringBuilder:append	(Ljava/lang/String;)Ljava/lang/StringBuilder;
/*      */     //   202: aload_0
/*      */     //   203: getfield 30	mz:jdField_a_of_type_Mx	Lmx;
/*      */     //   206: getfield 26	mx:jdField_a_of_type_Q	Lq;
/*      */     //   209: invokevirtual 42	java/lang/StringBuilder:append	(Ljava/lang/Object;)Ljava/lang/StringBuilder;
/*      */     //   212: ldc 2
/*      */     //   214: invokevirtual 43	java/lang/StringBuilder:append	(Ljava/lang/String;)Ljava/lang/StringBuilder;
/*      */     //   217: aload_0
/*      */     //   218: getfield 29	mz:jdField_a_of_type_JavaUtilArrayList	Ljava/util/ArrayList;
/*      */     //   221: invokevirtual 48	java/util/ArrayList:size	()I
/*      */     //   224: invokevirtual 40	java/lang/StringBuilder:append	(I)Ljava/lang/StringBuilder;
/*      */     //   227: ldc 4
/*      */     //   229: invokevirtual 43	java/lang/StringBuilder:append	(Ljava/lang/String;)Ljava/lang/StringBuilder;
/*      */     //   232: invokestatic 45	java/lang/System:currentTimeMillis	()J
/*      */     //   235: lload_2
/*      */     //   236: lsub
/*      */     //   237: invokevirtual 41	java/lang/StringBuilder:append	(J)Ljava/lang/StringBuilder;
/*      */     //   240: ldc 3
/*      */     //   242: invokevirtual 43	java/lang/StringBuilder:append	(Ljava/lang/String;)Ljava/lang/StringBuilder;
/*      */     //   245: invokevirtual 44	java/lang/StringBuilder:toString	()Ljava/lang/String;
/*      */     //   248: invokevirtual 34	java/io/PrintStream:println	(Ljava/lang/String;)V
/*      */     //   251: aload_0
/*      */     //   252: getfield 30	mz:jdField_a_of_type_Mx	Lmx;
/*      */     //   255: invokestatic 51	mx:a	(Lmx;)Z
/*      */     //   258: pop
/*      */     //   259: goto +16 -> 275
/*      */     //   262: invokevirtual 33	java/io/IOException:printStackTrace	()V
/*      */     //   265: goto +10 -> 275
/*      */     //   268: invokevirtual 46	java/sql/SQLException:printStackTrace	()V
/*      */     //   271: goto +4 -> 275
/*      */     //   274: athrow
/*      */     //   275: aload_1
/*      */     //   276: monitorexit
/*      */     //   277: return
/*      */     //   278: astore_2
/*      */     //   279: aload_1
/*      */     //   280: monitorexit
/*      */     //   281: aload_2
/*      */     //   282: athrow
/*      */     //
/*      */     // Exception table:
/*      */     //   from	to	target	type
/*      */     //   118	145	148	java/io/IOException
/*      */     //   118	145	154	java/lang/Exception
/*      */     //   10	259	262	java/io/IOException
/*      */     //   10	259	268	java/sql/SQLException
/*      */     //   10	259	274	finally
/*      */     //   262	265	274	finally
/*      */     //   268	271	274	finally
/*      */     //   10	277	278	finally
/*      */   }
/*      */ }

/* Location:           C:\Users\Raul\Desktop\StarMade\StarMade.jar
 * Qualified Name:     mz
 * JD-Core Version:    0.6.2
 */