/*   1:    */package org.schema.game.client.controller;
/*   2:    */
/*   3:    */import java.io.PrintStream;
/*   4:    */import java.sql.SQLException;
/*   5:    */
/*   6:    */public class SQLServerJavaDB
/*   7:    */{
/*   8:    */  /* Error */
/*   9:    */  public static void main(String[] paramArrayOfString)
/*  10:    */  {
/*  11:    */    // Byte code:
/*  12:    */    //   0: new 73	org/schema/game/client/controller/SQLServerJavaDB
/*  13:    */    //   3: dup
/*  14:    */    //   4: invokespecial 105	org/schema/game/client/controller/SQLServerJavaDB:<init>	()V
/*  15:    */    //   7: aload_0
/*  16:    */    //   8: astore_1
/*  17:    */    //   9: dup
/*  18:    */    //   10: astore_0
/*  19:    */    //   11: aload_1
/*  20:    */    //   12: astore_2
/*  21:    */    //   13: astore_1
/*  22:    */    //   14: aload_2
/*  23:    */    //   15: arraylength
/*  24:    */    //   16: ifle +32 -> 48
/*  25:    */    //   19: aload_2
/*  26:    */    //   20: iconst_0
/*  27:    */    //   21: aaload
/*  28:    */    //   22: ldc 40
/*  29:    */    //   24: invokevirtual 87	java/lang/String:equalsIgnoreCase	(Ljava/lang/String;)Z
/*  30:    */    //   27: ifeq +21 -> 48
/*  31:    */    //   30: aload_1
/*  32:    */    //   31: ldc 40
/*  33:    */    //   33: putfield 76	org/schema/game/client/controller/SQLServerJavaDB:a	Ljava/lang/String;
/*  34:    */    //   36: aload_1
/*  35:    */    //   37: ldc 47
/*  36:    */    //   39: putfield 77	org/schema/game/client/controller/SQLServerJavaDB:b	Ljava/lang/String;
/*  37:    */    //   42: aload_1
/*  38:    */    //   43: ldc 45
/*  39:    */    //   45: putfield 78	org/schema/game/client/controller/SQLServerJavaDB:c	Ljava/lang/String;
/*  40:    */    //   48: getstatic 75	java/lang/System:out	Ljava/io/PrintStream;
/*  41:    */    //   51: new 62	java/lang/StringBuilder
/*  42:    */    //   54: dup
/*  43:    */    //   55: ldc 28
/*  44:    */    //   57: invokespecial 89	java/lang/StringBuilder:<init>	(Ljava/lang/String;)V
/*  45:    */    //   60: aload_0
/*  46:    */    //   61: getfield 76	org/schema/game/client/controller/SQLServerJavaDB:a	Ljava/lang/String;
/*  47:    */    //   64: invokevirtual 91	java/lang/StringBuilder:append	(Ljava/lang/String;)Ljava/lang/StringBuilder;
/*  48:    */    //   67: ldc 11
/*  49:    */    //   69: invokevirtual 91	java/lang/StringBuilder:append	(Ljava/lang/String;)Ljava/lang/StringBuilder;
/*  50:    */    //   72: invokevirtual 92	java/lang/StringBuilder:toString	()Ljava/lang/String;
/*  51:    */    //   75: invokevirtual 79	java/io/PrintStream:println	(Ljava/lang/String;)V
/*  52:    */    //   78: aload_0
/*  53:    */    //   79: astore_1
/*  54:    */    //   80: aload_1
/*  55:    */    //   81: getfield 77	org/schema/game/client/controller/SQLServerJavaDB:b	Ljava/lang/String;
/*  56:    */    //   84: invokestatic 80	java/lang/Class:forName	(Ljava/lang/String;)Ljava/lang/Class;
/*  57:    */    //   87: invokevirtual 81	java/lang/Class:newInstance	()Ljava/lang/Object;
/*  58:    */    //   90: pop
/*  59:    */    //   91: getstatic 75	java/lang/System:out	Ljava/io/PrintStream;
/*  60:    */    //   94: ldc 23
/*  61:    */    //   96: invokevirtual 79	java/io/PrintStream:println	(Ljava/lang/String;)V
/*  62:    */    //   99: goto +116 -> 215
/*  63:    */    //   102: astore_2
/*  64:    */    //   103: getstatic 74	java/lang/System:err	Ljava/io/PrintStream;
/*  65:    */    //   106: new 62	java/lang/StringBuilder
/*  66:    */    //   109: dup
/*  67:    */    //   110: ldc 7
/*  68:    */    //   112: invokespecial 89	java/lang/StringBuilder:<init>	(Ljava/lang/String;)V
/*  69:    */    //   115: aload_1
/*  70:    */    //   116: getfield 77	org/schema/game/client/controller/SQLServerJavaDB:b	Ljava/lang/String;
/*  71:    */    //   119: invokevirtual 91	java/lang/StringBuilder:append	(Ljava/lang/String;)Ljava/lang/StringBuilder;
/*  72:    */    //   122: invokevirtual 92	java/lang/StringBuilder:toString	()Ljava/lang/String;
/*  73:    */    //   125: invokevirtual 79	java/io/PrintStream:println	(Ljava/lang/String;)V
/*  74:    */    //   128: getstatic 74	java/lang/System:err	Ljava/io/PrintStream;
/*  75:    */    //   131: ldc 25
/*  76:    */    //   133: invokevirtual 79	java/io/PrintStream:println	(Ljava/lang/String;)V
/*  77:    */    //   136: aload_2
/*  78:    */    //   137: getstatic 74	java/lang/System:err	Ljava/io/PrintStream;
/*  79:    */    //   140: invokevirtual 82	java/lang/ClassNotFoundException:printStackTrace	(Ljava/io/PrintStream;)V
/*  80:    */    //   143: goto +72 -> 215
/*  81:    */    //   146: astore_2
/*  82:    */    //   147: getstatic 74	java/lang/System:err	Ljava/io/PrintStream;
/*  83:    */    //   150: new 62	java/lang/StringBuilder
/*  84:    */    //   153: dup
/*  85:    */    //   154: ldc 6
/*  86:    */    //   156: invokespecial 89	java/lang/StringBuilder:<init>	(Ljava/lang/String;)V
/*  87:    */    //   159: aload_1
/*  88:    */    //   160: getfield 77	org/schema/game/client/controller/SQLServerJavaDB:b	Ljava/lang/String;
/*  89:    */    //   163: invokevirtual 91	java/lang/StringBuilder:append	(Ljava/lang/String;)Ljava/lang/StringBuilder;
/*  90:    */    //   166: invokevirtual 92	java/lang/StringBuilder:toString	()Ljava/lang/String;
/*  91:    */    //   169: invokevirtual 79	java/io/PrintStream:println	(Ljava/lang/String;)V
/*  92:    */    //   172: aload_2
/*  93:    */    //   173: getstatic 74	java/lang/System:err	Ljava/io/PrintStream;
/*  94:    */    //   176: invokevirtual 84	java/lang/InstantiationException:printStackTrace	(Ljava/io/PrintStream;)V
/*  95:    */    //   179: goto +36 -> 215
/*  96:    */    //   182: astore_2
/*  97:    */    //   183: getstatic 74	java/lang/System:err	Ljava/io/PrintStream;
/*  98:    */    //   186: new 62	java/lang/StringBuilder
/*  99:    */    //   189: dup
/* 100:    */    //   190: ldc 5
/* 101:    */    //   192: invokespecial 89	java/lang/StringBuilder:<init>	(Ljava/lang/String;)V
/* 102:    */    //   195: aload_1
/* 103:    */    //   196: getfield 77	org/schema/game/client/controller/SQLServerJavaDB:b	Ljava/lang/String;
/* 104:    */    //   199: invokevirtual 91	java/lang/StringBuilder:append	(Ljava/lang/String;)Ljava/lang/StringBuilder;
/* 105:    */    //   202: invokevirtual 92	java/lang/StringBuilder:toString	()Ljava/lang/String;
/* 106:    */    //   205: invokevirtual 79	java/io/PrintStream:println	(Ljava/lang/String;)V
/* 107:    */    //   208: aload_2
/* 108:    */    //   209: getstatic 74	java/lang/System:err	Ljava/io/PrintStream;
/* 109:    */    //   212: invokevirtual 83	java/lang/IllegalAccessException:printStackTrace	(Ljava/io/PrintStream;)V
/* 110:    */    //   215: aconst_null
/* 111:    */    //   216: astore_1
/* 112:    */    //   217: new 71	java/util/ArrayList
/* 113:    */    //   220: dup
/* 114:    */    //   221: invokespecial 99	java/util/ArrayList:<init>	()V
/* 115:    */    //   224: astore_2
/* 116:    */    //   225: aconst_null
/* 117:    */    //   226: astore 4
/* 118:    */    //   228: aconst_null
/* 119:    */    //   229: astore 5
/* 120:    */    //   231: new 72	java/util/Properties
/* 121:    */    //   234: dup
/* 122:    */    //   235: invokespecial 103	java/util/Properties:<init>	()V
/* 123:    */    //   238: dup
/* 124:    */    //   239: astore_3
/* 125:    */    //   240: ldc 53
/* 126:    */    //   242: ldc 50
/* 127:    */    //   244: invokevirtual 104	java/util/Properties:put	(Ljava/lang/Object;Ljava/lang/Object;)Ljava/lang/Object;
/* 128:    */    //   247: pop
/* 129:    */    //   248: aload_3
/* 130:    */    //   249: ldc 49
/* 131:    */    //   251: ldc 50
/* 132:    */    //   253: invokevirtual 104	java/util/Properties:put	(Ljava/lang/Object;Ljava/lang/Object;)Ljava/lang/Object;
/* 133:    */    //   256: pop
/* 134:    */    //   257: ldc 51
/* 135:    */    //   259: astore 4
/* 136:    */    //   261: new 62	java/lang/StringBuilder
/* 137:    */    //   264: dup
/* 138:    */    //   265: invokespecial 88	java/lang/StringBuilder:<init>	()V
/* 139:    */    //   268: aload_0
/* 140:    */    //   269: getfield 78	org/schema/game/client/controller/SQLServerJavaDB:c	Ljava/lang/String;
/* 141:    */    //   272: invokevirtual 91	java/lang/StringBuilder:append	(Ljava/lang/String;)Ljava/lang/StringBuilder;
/* 142:    */    //   275: aload 4
/* 143:    */    //   277: invokevirtual 91	java/lang/StringBuilder:append	(Ljava/lang/String;)Ljava/lang/StringBuilder;
/* 144:    */    //   280: ldc 12
/* 145:    */    //   282: invokevirtual 91	java/lang/StringBuilder:append	(Ljava/lang/String;)Ljava/lang/StringBuilder;
/* 146:    */    //   285: invokevirtual 92	java/lang/StringBuilder:toString	()Ljava/lang/String;
/* 147:    */    //   288: aload_3
/* 148:    */    //   289: invokestatic 94	java/sql/DriverManager:getConnection	(Ljava/lang/String;Ljava/util/Properties;)Ljava/sql/Connection;
/* 149:    */    //   292: astore_1
/* 150:    */    //   293: getstatic 75	java/lang/System:out	Ljava/io/PrintStream;
/* 151:    */    //   296: new 62	java/lang/StringBuilder
/* 152:    */    //   299: dup
/* 153:    */    //   300: ldc 14
/* 154:    */    //   302: invokespecial 89	java/lang/StringBuilder:<init>	(Ljava/lang/String;)V
/* 155:    */    //   305: aload 4
/* 156:    */    //   307: invokevirtual 91	java/lang/StringBuilder:append	(Ljava/lang/String;)Ljava/lang/StringBuilder;
/* 157:    */    //   310: invokevirtual 92	java/lang/StringBuilder:toString	()Ljava/lang/String;
/* 158:    */    //   313: invokevirtual 79	java/io/PrintStream:println	(Ljava/lang/String;)V
/* 159:    */    //   316: aload_1
/* 160:    */    //   317: iconst_0
/* 161:    */    //   318: invokeinterface 112 2 0
/* 162:    */    //   323: aload_1
/* 163:    */    //   324: invokeinterface 110 1 0
/* 164:    */    //   329: astore 4
/* 165:    */    //   331: aload_2
/* 166:    */    //   332: aload 4
/* 167:    */    //   334: invokevirtual 100	java/util/ArrayList:add	(Ljava/lang/Object;)Z
/* 168:    */    //   337: pop
/* 169:    */    //   338: aload 4
/* 170:    */    //   340: ldc 39
/* 171:    */    //   342: invokeinterface 120 2 0
/* 172:    */    //   347: pop
/* 173:    */    //   348: getstatic 75	java/lang/System:out	Ljava/io/PrintStream;
/* 174:    */    //   351: ldc 15
/* 175:    */    //   353: invokevirtual 79	java/io/PrintStream:println	(Ljava/lang/String;)V
/* 176:    */    //   356: aload_1
/* 177:    */    //   357: ldc 43
/* 178:    */    //   359: invokeinterface 111 2 0
/* 179:    */    //   364: astore_3
/* 180:    */    //   365: aload_2
/* 181:    */    //   366: aload_3
/* 182:    */    //   367: invokevirtual 100	java/util/ArrayList:add	(Ljava/lang/Object;)Z
/* 183:    */    //   370: pop
/* 184:    */    //   371: aload_3
/* 185:    */    //   372: iconst_1
/* 186:    */    //   373: sipush 1956
/* 187:    */    //   376: invokeinterface 114 3 0
/* 188:    */    //   381: aload_3
/* 189:    */    //   382: iconst_2
/* 190:    */    //   383: ldc 35
/* 191:    */    //   385: invokeinterface 115 3 0
/* 192:    */    //   390: aload_3
/* 193:    */    //   391: invokeinterface 113 1 0
/* 194:    */    //   396: pop
/* 195:    */    //   397: getstatic 75	java/lang/System:out	Ljava/io/PrintStream;
/* 196:    */    //   400: ldc 21
/* 197:    */    //   402: invokevirtual 79	java/io/PrintStream:println	(Ljava/lang/String;)V
/* 198:    */    //   405: aload_3
/* 199:    */    //   406: iconst_1
/* 200:    */    //   407: sipush 1910
/* 201:    */    //   410: invokeinterface 114 3 0
/* 202:    */    //   415: aload_3
/* 203:    */    //   416: iconst_2
/* 204:    */    //   417: ldc 31
/* 205:    */    //   419: invokeinterface 115 3 0
/* 206:    */    //   424: aload_3
/* 207:    */    //   425: invokeinterface 113 1 0
/* 208:    */    //   430: pop
/* 209:    */    //   431: getstatic 75	java/lang/System:out	Ljava/io/PrintStream;
/* 210:    */    //   434: ldc 20
/* 211:    */    //   436: invokevirtual 79	java/io/PrintStream:println	(Ljava/lang/String;)V
/* 212:    */    //   439: aload_1
/* 213:    */    //   440: ldc 52
/* 214:    */    //   442: invokeinterface 111 2 0
/* 215:    */    //   447: astore_3
/* 216:    */    //   448: aload_2
/* 217:    */    //   449: aload_3
/* 218:    */    //   450: invokevirtual 100	java/util/ArrayList:add	(Ljava/lang/Object;)Z
/* 219:    */    //   453: pop
/* 220:    */    //   454: aload_3
/* 221:    */    //   455: iconst_1
/* 222:    */    //   456: sipush 180
/* 223:    */    //   459: invokeinterface 114 3 0
/* 224:    */    //   464: aload_3
/* 225:    */    //   465: iconst_2
/* 226:    */    //   466: ldc 19
/* 227:    */    //   468: invokeinterface 115 3 0
/* 228:    */    //   473: aload_3
/* 229:    */    //   474: iconst_3
/* 230:    */    //   475: sipush 1956
/* 231:    */    //   478: invokeinterface 114 3 0
/* 232:    */    //   483: aload_3
/* 233:    */    //   484: invokeinterface 113 1 0
/* 234:    */    //   489: pop
/* 235:    */    //   490: getstatic 75	java/lang/System:out	Ljava/io/PrintStream;
/* 236:    */    //   493: ldc 33
/* 237:    */    //   495: invokevirtual 79	java/io/PrintStream:println	(Ljava/lang/String;)V
/* 238:    */    //   498: aload_3
/* 239:    */    //   499: iconst_1
/* 240:    */    //   500: sipush 300
/* 241:    */    //   503: invokeinterface 114 3 0
/* 242:    */    //   508: aload_3
/* 243:    */    //   509: iconst_2
/* 244:    */    //   510: ldc 22
/* 245:    */    //   512: invokeinterface 115 3 0
/* 246:    */    //   517: aload_3
/* 247:    */    //   518: iconst_3
/* 248:    */    //   519: sipush 180
/* 249:    */    //   522: invokeinterface 114 3 0
/* 250:    */    //   527: aload_3
/* 251:    */    //   528: invokeinterface 113 1 0
/* 252:    */    //   533: pop
/* 253:    */    //   534: getstatic 75	java/lang/System:out	Ljava/io/PrintStream;
/* 254:    */    //   537: ldc 32
/* 255:    */    //   539: invokevirtual 79	java/io/PrintStream:println	(Ljava/lang/String;)V
/* 256:    */    //   542: aload 4
/* 257:    */    //   544: ldc 26
/* 258:    */    //   546: invokeinterface 121 2 0
/* 259:    */    //   551: astore 5
/* 260:    */    //   553: iconst_0
/* 261:    */    //   554: istore 6
/* 262:    */    //   556: aload 5
/* 263:    */    //   558: invokeinterface 118 1 0
/* 264:    */    //   563: ifne +11 -> 574
/* 265:    */    //   566: iconst_1
/* 266:    */    //   567: istore 6
/* 267:    */    //   569: ldc 24
/* 268:    */    //   571: invokestatic 106	org/schema/game/client/controller/SQLServerJavaDB:a	(Ljava/lang/String;)V
/* 269:    */    //   574: aload 5
/* 270:    */    //   576: iconst_1
/* 271:    */    //   577: invokeinterface 117 2 0
/* 272:    */    //   582: dup
/* 273:    */    //   583: istore_3
/* 274:    */    //   584: sipush 300
/* 275:    */    //   587: if_icmpeq +25 -> 612
/* 276:    */    //   590: iconst_1
/* 277:    */    //   591: istore 6
/* 278:    */    //   593: new 62	java/lang/StringBuilder
/* 279:    */    //   596: dup
/* 280:    */    //   597: ldc 37
/* 281:    */    //   599: invokespecial 89	java/lang/StringBuilder:<init>	(Ljava/lang/String;)V
/* 282:    */    //   602: iload_3
/* 283:    */    //   603: invokevirtual 90	java/lang/StringBuilder:append	(I)Ljava/lang/StringBuilder;
/* 284:    */    //   606: invokevirtual 92	java/lang/StringBuilder:toString	()Ljava/lang/String;
/* 285:    */    //   609: invokestatic 106	org/schema/game/client/controller/SQLServerJavaDB:a	(Ljava/lang/String;)V
/* 286:    */    //   612: aload 5
/* 287:    */    //   614: invokeinterface 118 1 0
/* 288:    */    //   619: ifne +11 -> 630
/* 289:    */    //   622: iconst_1
/* 290:    */    //   623: istore 6
/* 291:    */    //   625: ldc 29
/* 292:    */    //   627: invokestatic 106	org/schema/game/client/controller/SQLServerJavaDB:a	(Ljava/lang/String;)V
/* 293:    */    //   630: aload 5
/* 294:    */    //   632: iconst_1
/* 295:    */    //   633: invokeinterface 117 2 0
/* 296:    */    //   638: dup
/* 297:    */    //   639: istore_3
/* 298:    */    //   640: sipush 1910
/* 299:    */    //   643: if_icmpeq +25 -> 668
/* 300:    */    //   646: iconst_1
/* 301:    */    //   647: istore 6
/* 302:    */    //   649: new 62	java/lang/StringBuilder
/* 303:    */    //   652: dup
/* 304:    */    //   653: ldc 36
/* 305:    */    //   655: invokespecial 89	java/lang/StringBuilder:<init>	(Ljava/lang/String;)V
/* 306:    */    //   658: iload_3
/* 307:    */    //   659: invokevirtual 90	java/lang/StringBuilder:append	(I)Ljava/lang/StringBuilder;
/* 308:    */    //   662: invokevirtual 92	java/lang/StringBuilder:toString	()Ljava/lang/String;
/* 309:    */    //   665: invokestatic 106	org/schema/game/client/controller/SQLServerJavaDB:a	(Ljava/lang/String;)V
/* 310:    */    //   668: aload 5
/* 311:    */    //   670: invokeinterface 118 1 0
/* 312:    */    //   675: ifeq +11 -> 686
/* 313:    */    //   678: iconst_1
/* 314:    */    //   679: istore 6
/* 315:    */    //   681: ldc 30
/* 316:    */    //   683: invokestatic 106	org/schema/game/client/controller/SQLServerJavaDB:a	(Ljava/lang/String;)V
/* 317:    */    //   686: iload 6
/* 318:    */    //   688: ifne +11 -> 699
/* 319:    */    //   691: getstatic 75	java/lang/System:out	Ljava/io/PrintStream;
/* 320:    */    //   694: ldc 34
/* 321:    */    //   696: invokevirtual 79	java/io/PrintStream:println	(Ljava/lang/String;)V
/* 322:    */    //   699: aload 4
/* 323:    */    //   701: ldc 41
/* 324:    */    //   703: invokeinterface 120 2 0
/* 325:    */    //   708: pop
/* 326:    */    //   709: getstatic 75	java/lang/System:out	Ljava/io/PrintStream;
/* 327:    */    //   712: ldc 18
/* 328:    */    //   714: invokevirtual 79	java/io/PrintStream:println	(Ljava/lang/String;)V
/* 329:    */    //   717: aload_1
/* 330:    */    //   718: invokeinterface 109 1 0
/* 331:    */    //   723: getstatic 75	java/lang/System:out	Ljava/io/PrintStream;
/* 332:    */    //   726: ldc 13
/* 333:    */    //   728: invokevirtual 79	java/io/PrintStream:println	(Ljava/lang/String;)V
/* 334:    */    //   731: aload_0
/* 335:    */    //   732: getfield 76	org/schema/game/client/controller/SQLServerJavaDB:a	Ljava/lang/String;
/* 336:    */    //   735: ldc 42
/* 337:    */    //   737: invokevirtual 86	java/lang/String:equals	(Ljava/lang/Object;)Z
/* 338:    */    //   740: ifeq +57 -> 797
/* 339:    */    //   743: ldc 46
/* 340:    */    //   745: invokestatic 93	java/sql/DriverManager:getConnection	(Ljava/lang/String;)Ljava/sql/Connection;
/* 341:    */    //   748: pop
/* 342:    */    //   749: goto +48 -> 797
/* 343:    */    //   752: dup
/* 344:    */    //   753: astore_0
/* 345:    */    //   754: invokevirtual 95	java/sql/SQLException:getErrorCode	()I
/* 346:    */    //   757: ldc 1
/* 347:    */    //   759: if_icmpne +26 -> 785
/* 348:    */    //   762: ldc 38
/* 349:    */    //   764: aload_0
/* 350:    */    //   765: invokevirtual 98	java/sql/SQLException:getSQLState	()Ljava/lang/String;
/* 351:    */    //   768: invokevirtual 86	java/lang/String:equals	(Ljava/lang/Object;)Z
/* 352:    */    //   771: ifeq +14 -> 785
/* 353:    */    //   774: getstatic 75	java/lang/System:out	Ljava/io/PrintStream;
/* 354:    */    //   777: ldc 17
/* 355:    */    //   779: invokevirtual 79	java/io/PrintStream:println	(Ljava/lang/String;)V
/* 356:    */    //   782: goto +15 -> 797
/* 357:    */    //   785: getstatic 74	java/lang/System:err	Ljava/io/PrintStream;
/* 358:    */    //   788: ldc 16
/* 359:    */    //   790: invokevirtual 79	java/io/PrintStream:println	(Ljava/lang/String;)V
/* 360:    */    //   793: aload_0
/* 361:    */    //   794: invokestatic 107	org/schema/game/client/controller/SQLServerJavaDB:a	(Ljava/sql/SQLException;)V
/* 362:    */    //   797: aload 5
/* 363:    */    //   799: ifnull +10 -> 809
/* 364:    */    //   802: aload 5
/* 365:    */    //   804: invokeinterface 116 1 0
/* 366:    */    //   809: goto +6 -> 815
/* 367:    */    //   812: invokestatic 107	org/schema/game/client/controller/SQLServerJavaDB:a	(Ljava/sql/SQLException;)V
/* 368:    */    //   815: aload_2
/* 369:    */    //   816: invokevirtual 101	java/util/ArrayList:isEmpty	()Z
/* 370:    */    //   819: ifne +34 -> 853
/* 371:    */    //   822: aload_2
/* 372:    */    //   823: iconst_0
/* 373:    */    //   824: invokevirtual 102	java/util/ArrayList:remove	(I)Ljava/lang/Object;
/* 374:    */    //   827: checkcast 70	java/sql/Statement
/* 375:    */    //   830: astore 4
/* 376:    */    //   832: aload 4
/* 377:    */    //   834: ifnull +10 -> 844
/* 378:    */    //   837: aload 4
/* 379:    */    //   839: invokeinterface 119 1 0
/* 380:    */    //   844: goto -29 -> 815
/* 381:    */    //   847: invokestatic 107	org/schema/game/client/controller/SQLServerJavaDB:a	(Ljava/sql/SQLException;)V
/* 382:    */    //   850: goto -35 -> 815
/* 383:    */    //   853: aload_1
/* 384:    */    //   854: ifnull +9 -> 863
/* 385:    */    //   857: aload_1
/* 386:    */    //   858: invokeinterface 108 1 0
/* 387:    */    //   863: goto +159 -> 1022
/* 388:    */    //   866: invokestatic 107	org/schema/game/client/controller/SQLServerJavaDB:a	(Ljava/sql/SQLException;)V
/* 389:    */    //   869: goto +153 -> 1022
/* 390:    */    //   872: invokestatic 107	org/schema/game/client/controller/SQLServerJavaDB:a	(Ljava/sql/SQLException;)V
/* 391:    */    //   875: aload 5
/* 392:    */    //   877: ifnull +10 -> 887
/* 393:    */    //   880: aload 5
/* 394:    */    //   882: invokeinterface 116 1 0
/* 395:    */    //   887: goto +6 -> 893
/* 396:    */    //   890: invokestatic 107	org/schema/game/client/controller/SQLServerJavaDB:a	(Ljava/sql/SQLException;)V
/* 397:    */    //   893: aload_2
/* 398:    */    //   894: invokevirtual 101	java/util/ArrayList:isEmpty	()Z
/* 399:    */    //   897: ifne +34 -> 931
/* 400:    */    //   900: aload_2
/* 401:    */    //   901: iconst_0
/* 402:    */    //   902: invokevirtual 102	java/util/ArrayList:remove	(I)Ljava/lang/Object;
/* 403:    */    //   905: checkcast 70	java/sql/Statement
/* 404:    */    //   908: astore 4
/* 405:    */    //   910: aload 4
/* 406:    */    //   912: ifnull +10 -> 922
/* 407:    */    //   915: aload 4
/* 408:    */    //   917: invokeinterface 119 1 0
/* 409:    */    //   922: goto -29 -> 893
/* 410:    */    //   925: invokestatic 107	org/schema/game/client/controller/SQLServerJavaDB:a	(Ljava/sql/SQLException;)V
/* 411:    */    //   928: goto -35 -> 893
/* 412:    */    //   931: aload_1
/* 413:    */    //   932: ifnull +9 -> 941
/* 414:    */    //   935: aload_1
/* 415:    */    //   936: invokeinterface 108 1 0
/* 416:    */    //   941: goto +81 -> 1022
/* 417:    */    //   944: invokestatic 107	org/schema/game/client/controller/SQLServerJavaDB:a	(Ljava/sql/SQLException;)V
/* 418:    */    //   947: goto +75 -> 1022
/* 419:    */    //   950: astore_0
/* 420:    */    //   951: aload 5
/* 421:    */    //   953: ifnull +10 -> 963
/* 422:    */    //   956: aload 5
/* 423:    */    //   958: invokeinterface 116 1 0
/* 424:    */    //   963: goto +6 -> 969
/* 425:    */    //   966: invokestatic 107	org/schema/game/client/controller/SQLServerJavaDB:a	(Ljava/sql/SQLException;)V
/* 426:    */    //   969: aload_2
/* 427:    */    //   970: invokevirtual 101	java/util/ArrayList:isEmpty	()Z
/* 428:    */    //   973: ifne +31 -> 1004
/* 429:    */    //   976: aload_2
/* 430:    */    //   977: iconst_0
/* 431:    */    //   978: invokevirtual 102	java/util/ArrayList:remove	(I)Ljava/lang/Object;
/* 432:    */    //   981: checkcast 70	java/sql/Statement
/* 433:    */    //   984: astore_3
/* 434:    */    //   985: aload_3
/* 435:    */    //   986: ifnull +9 -> 995
/* 436:    */    //   989: aload_3
/* 437:    */    //   990: invokeinterface 119 1 0
/* 438:    */    //   995: goto -26 -> 969
/* 439:    */    //   998: invokestatic 107	org/schema/game/client/controller/SQLServerJavaDB:a	(Ljava/sql/SQLException;)V
/* 440:    */    //   1001: goto -32 -> 969
/* 441:    */    //   1004: aload_1
/* 442:    */    //   1005: ifnull +9 -> 1014
/* 443:    */    //   1008: aload_1
/* 444:    */    //   1009: invokeinterface 108 1 0
/* 445:    */    //   1014: goto +6 -> 1020
/* 446:    */    //   1017: invokestatic 107	org/schema/game/client/controller/SQLServerJavaDB:a	(Ljava/sql/SQLException;)V
/* 447:    */    //   1020: aload_0
/* 448:    */    //   1021: athrow
/* 449:    */    //   1022: getstatic 75	java/lang/System:out	Ljava/io/PrintStream;
/* 450:    */    //   1025: ldc 27
/* 451:    */    //   1027: invokevirtual 79	java/io/PrintStream:println	(Ljava/lang/String;)V
/* 452:    */    //   1030: return
/* 453:    */    // Line number table:
/* 454:    */    //   Java source line #90	-> byte code offset #0
/* 455:    */    //   Java source line #91	-> byte code offset #1022
/* 456:    */    //   Java source line #92	-> byte code offset #1030
/* 457:    */    // Local variable table:
/* 458:    */    //   start	length	slot	name	signature
/* 459:    */    //   0	1031	0	paramArrayOfString	String[]
/* 460:    */    //   8	1001	1	localObject1	Object
/* 461:    */    //   12	8	2	localObject2	Object
/* 462:    */    //   102	35	2	localClassNotFoundException	java.lang.ClassNotFoundException
/* 463:    */    //   146	27	2	localInstantiationException	java.lang.InstantiationException
/* 464:    */    //   182	27	2	localIllegalAccessException	java.lang.IllegalAccessException
/* 465:    */    //   224	753	2	localArrayList	java.util.ArrayList
/* 466:    */    //   239	289	3	localObject3	Object
/* 467:    */    //   583	76	3	i	int
/* 468:    */    //   984	6	3	localStatement	java.sql.Statement
/* 469:    */    //   226	690	4	localObject4	Object
/* 470:    */    //   229	728	5	localResultSet	java.sql.ResultSet
/* 471:    */    //   554	133	6	j	int
/* 472:    */    //   752	1	13	localSQLException1	SQLException
/* 473:    */    //   812	1	14	localSQLException2	SQLException
/* 474:    */    //   847	1	15	localSQLException3	SQLException
/* 475:    */    //   866	1	16	localSQLException4	SQLException
/* 476:    */    //   872	1	17	localSQLException5	SQLException
/* 477:    */    //   890	1	18	localSQLException6	SQLException
/* 478:    */    //   925	1	19	localSQLException7	SQLException
/* 479:    */    //   944	1	20	localSQLException8	SQLException
/* 480:    */    //   966	1	21	localSQLException9	SQLException
/* 481:    */    //   998	1	22	localSQLException10	SQLException
/* 482:    */    //   1017	1	23	localSQLException11	SQLException
/* 483:    */    // Exception table:
/* 484:    */    //   from	to	target	type
/* 485:    */    //   80	99	102	java/lang/ClassNotFoundException
/* 486:    */    //   80	99	146	java/lang/InstantiationException
/* 487:    */    //   80	99	182	java/lang/IllegalAccessException
/* 488:    */    //   743	749	752	java/sql/SQLException
/* 489:    */    //   797	809	812	java/sql/SQLException
/* 490:    */    //   832	844	847	java/sql/SQLException
/* 491:    */    //   853	863	866	java/sql/SQLException
/* 492:    */    //   231	797	872	java/sql/SQLException
/* 493:    */    //   875	887	890	java/sql/SQLException
/* 494:    */    //   910	922	925	java/sql/SQLException
/* 495:    */    //   931	941	944	java/sql/SQLException
/* 496:    */    //   231	797	950	finally
/* 497:    */    //   872	875	950	finally
/* 498:    */    //   951	963	966	java/sql/SQLException
/* 499:    */    //   985	995	998	java/sql/SQLException
/* 500:    */    //   1004	1014	1017	java/sql/SQLException
/* 501:    */  }
/* 502:    */  
/* 503:    */  private static void a(SQLException paramSQLException)
/* 504:    */  {
/* 505:103 */    while (paramSQLException != null)
/* 506:    */    {
/* 507:105 */      System.err.println("\n----- SQLException -----");
/* 508:106 */      System.err.println("  SQL State:  " + paramSQLException.getSQLState());
/* 509:107 */      System.err.println("  Error Code: " + paramSQLException.getErrorCode());
/* 510:108 */      System.err.println("  Message:    " + paramSQLException.getMessage());
/* 511:    */      
/* 513:111 */      paramSQLException = paramSQLException.getNextException();
/* 514:    */    }
/* 515:    */  }
/* 516:    */  
/* 517:115 */  private String a = "embedded";
/* 518:    */  
/* 519:117 */  private String b = "org.apache.derby.jdbc.EmbeddedDriver";
/* 520:    */  
/* 521:119 */  private String c = "jdbc:derby:";
/* 522:    */  
/* 885:    */  private static void a(String paramString)
/* 886:    */  {
/* 887:485 */    System.err.println("\nData verification failed:");
/* 888:486 */    System.err.println("\t" + paramString);
/* 889:    */  }
/* 890:    */}


/* Location:           C:\Users\Raul\Desktop\StarMade\StarMade.jar
 * Qualified Name:     org.schema.game.client.controller.SQLServerJavaDB
 * JD-Core Version:    0.7.0-SNAPSHOT-20130630
 */